LICENSE
README.rst
setup.py
django_multi_tenancy.egg-info/PKG-INFO
django_multi_tenancy.egg-info/SOURCES.txt
django_multi_tenancy.egg-info/dependency_links.txt
django_multi_tenancy.egg-info/requires.txt
django_multi_tenancy.egg-info/top_level.txt
multi_tenant/__init__.py
multi_tenant/const.py
multi_tenant/local.py
multi_tenant/proxy/__init__.py
multi_tenant/proxy/admin.py
multi_tenant/proxy/apps.py
multi_tenant/proxy/models.py
multi_tenant/proxy/tests.py
multi_tenant/proxy/views.py
multi_tenant/proxy/migrations/0001_initial.py
multi_tenant/proxy/migrations/__init__.py
multi_tenant/rest/__init__.py
multi_tenant/rest/admin.py
multi_tenant/rest/apps.py
multi_tenant/rest/models.py
multi_tenant/rest/migrations/__init__.py
multi_tenant/rest/patch/__init__.py
multi_tenant/rest/patch/request.py
multi_tenant/rest/permissions/__init__.py
multi_tenant/tenant/__init__.py
multi_tenant/tenant/admin.py
multi_tenant/tenant/apps.py
multi_tenant/tenant/backend.py
multi_tenant/tenant/signal.py
multi_tenant/tenant/tests.py
multi_tenant/tenant/views.py
multi_tenant/tenant/management/__init__.py
multi_tenant/tenant/management/commands/__init__.py
multi_tenant/tenant/management/commands/createtenant.py
multi_tenant/tenant/management/commands/multimigrate.py
multi_tenant/tenant/middleware/__init__.py
multi_tenant/tenant/middleware/authentication.py
multi_tenant/tenant/migrations/0001_initial.py
multi_tenant/tenant/migrations/__init__.py
multi_tenant/tenant/models/__init__.py
multi_tenant/tenant/models/tenant.py
multi_tenant/tenant/models/user.py
multi_tenant/tenant/patch/__init__.py
multi_tenant/tenant/patch/connection.py
multi_tenant/tenant/patch/contenttype.py
multi_tenant/tenant/patch/permission.py
multi_tenant/tenant/patch/user.py
multi_tenant/tenant/utils/__init__.py
multi_tenant/tenant/utils/db.py
multi_tenant/tenant/utils/pycrypt.py