Metadata-Version: 2.1
Name: django-multi-tenancy
Version: 0.1.3
Summary: Django multi tenant implementation
Home-page: https://github.com/AnsGoo/djangoMultiTenant
Author: ansgoo
Author-email: haiven_123@163.com
License: MIT Licence
Keywords: python,django,mult-tenant
Platform: any
Classifier: Development Status :: 5 - Production/Stable
Classifier: Programming Language :: Python
Classifier: Programming Language :: Python :: 3
Classifier: Programming Language :: Python :: 3 :: Only
Classifier: Programming Language :: Python :: 3.7
Classifier: Programming Language :: Python :: 3.8
Classifier: Programming Language :: Python :: 3.9
Classifier: License :: OSI Approved :: MIT License
Classifier: Operating System :: Unix
Classifier: Operating System :: POSIX :: Linux
Classifier: Environment :: Console
Classifier: Environment :: MacOS X
License-File: LICENSE
